setup.py
Flasky.egg-info/SOURCES.txt
flasky/__init__.py
flasky/flasky.py
flasky.egg-info/PKG-INFO
flasky.egg-info/SOURCES.txt
flasky.egg-info/dependency_links.txt
flasky.egg-info/top_level.txt
flasky/tests/__init__.py
flasky/tests/flasky_test.py